HousingPriceSP/__init__.py
HousingPriceSP/ingest_data.py
HousingPriceSP/logger.py
HousingPriceSP/score.py
HousingPriceSP/setup.py
HousingPriceSP/train.py
HousingPriceSP-1.1.0.dist-info/METADATA
HousingPriceSP-1.1.0.dist-info/WHEEL
HousingPriceSP-1.1.0.dist-info/top_level.txt
HousingPriceSP-1.1.0.dist-info/RECORD
