Metadata-Version: 2.1
Name: HousingPriceSP
Version: 1.1.0
Summary: Package to Predict housing Price!
Author: Prakash Singh
Requires-Python: >=3.6
